randomcov/__init__.py
randomcov/randomcorrelationmatrix.py
randomcov/randomcovariancematrix.py
randomcov/randomvariancevector.py
randomcov/benchmarkingutil/__init__.py
randomcov/benchmarkingutil/minvarleaderboard.py
randomcov/corrgens/__init__.py
randomcov/corrgens/allcorrgens.py
randomcov/corrgens/animals.py
randomcov/corrgens/lkj.py
randomcov/corrgens/residuals.py
randomcov/corrgens/walk.py
randomcov/corrgens/wishart.py
randomcov/corrutil/__init__.py
randomcov/corrutil/corrwalk.py
randomcov/corrutil/isvalidcorr.py
randomcov/corrutil/nearestcorr.py
randomcov/covutil/__init__.py
randomcov/covutil/geodesicinterpolation.py
randomcov/covutil/nearestposdef.py
randomcov/vargens/__init__.py
randomcov/vargens/allvargens.py
randomcov/vargens/lognormalvar.py
randomcov-0.0.15.dist-info/LICENSE
randomcov-0.0.15.dist-info/METADATA
randomcov-0.0.15.dist-info/WHEEL
randomcov-0.0.15.dist-info/entry_points.txt
randomcov-0.0.15.dist-info/top_level.txt
randomcov-0.0.15.dist-info/RECORD
